{
    "current_weather": {
        "ciudad": "La Serena",
        "descripcion": "niebla",
        "temperatura": 11.73,
        "humedad": 93,
        "viento": 1.03
    },
    "recent_news": [
        {
            "titulo": "Capital natural: cuando proteger la biodiversidad es un buen negocio",
            "fuente": "Latercera.com",
            "fecha": "2025-05-24T04:14:20Z"
        },
        {
            "titulo": "La ambiciosa meta del nuevo gerente general del negocio automotriz de ByD en Chile",
            "fuente": "Latercera.com",
            "fecha": "2025-05-24T04:00:00Z"
        },
        {
            "titulo": "Irlanda y Estonia: Los modelos económicos que atraen la mirada de los candidatos presidenciables",
            "fuente": "Latercera.com",
            "fecha": "2025-05-24T04:00:00Z"
        },
        {
            "titulo": "Parque Arauco Kennedy vs. Costanera Center: la contienda por ser el mall con más ventas en Chile",
            "fuente": "Latercera.com",
            "fecha": "2025-05-24T04:00:00Z"
        },
        {
            "titulo": "Experta en relación Asia-Latam: “Chile tiene que empezar a pensar en una nueva estrategia para promover sus propios intereses”",
            "fuente": "Latercera.com",
            "fecha": "2025-05-24T04:00:00Z"
        }
    ],
    "country_info": {
        "capital": "Santiago",
        "poblacion": 19116209,
        "moneda": "CLP"
    }
}